<?xml version="1.0" encoding="UTF-8"?>
<configuration>
    <!-- 日志存储路径 -->
    <property name="LOG_HOME" value="logs"/>

    <!-- 应用名称 -->
    <property name="APP_NAME" value="auth-center"/>

    <!-- 引入 Spring Boot 的日志配置（支持彩色日志） -->
    <conversionRule conversionWord="clr" converterClass="org.springframework.boot.logging.logback.ColorConverter"/>
    <conversionRule conversionWord="wex"
                    converterClass="org.springframework.boot.logging.logback.WhitespaceThrowableProxyConverter"/>
    <conversionRule conversionWord="wEx"
                    converterClass="org.springframework.boot.logging.logback.ExtendedWhitespaceThrowableProxyConverter"/>

    <!-- 日志输出格式 -->
    <property name="LOG_PATTERN" value="%d{yyyy-MM-dd HH:mm:ss.SSS} [%thread] %-5level %logger{50} - %msg%n"/>

    <!-- 彩色日志格式（控制台） -->
    <property name="CONSOLE_LOG_PATTERN"
              value="%clr(%d{yyyy-MM-dd HH:mm:ss.SSS}){faint} %clr([%thread]){magenta} %clr(%-5level){blue} %clr(%logger{50}){cyan} - %msg%n"/>

    <!-- ==================== 控制台输出 ==================== -->
    <appender name="CONSOLE" class="ch.qos.logback.core.ConsoleAppender">
        <encoder>
            <pattern>${CONSOLE_LOG_PATTERN}</pattern>
            <charset>UTF-8</charset>
        </encoder>
    </appender>

    <!-- ==================== DEBUG 日志 ==================== -->
    <appender name="DEBUG_FILE" class="ch.qos.logback.core.rolling.RollingFileAppender">
        <!-- 当前日志文件 -->
        <file>${LOG_HOME}/debug.log</file>

        <!-- 日志文件编码 -->
        <encoder>
            <pattern>${LOG_PATTERN}</pattern>
            <charset>UTF-8</charset>
        </encoder>

        <!-- 滚动策略：基于时间和大小 -->
        <rollingPolicy class="ch.qos.logback.core.rolling.SizeAndTimeBasedRollingPolicy">
            <!-- 归档日志文件名格式 -->
            <fileNamePattern>${LOG_HOME}/debug/debug.%d{yyyy-MM-dd}.%i.log</fileNamePattern>
            <!-- 单个日志文件最大大小 -->
            <maxFileSize>100MB</maxFileSize>
            <!-- 日志保留天数 -->
            <maxHistory>15</maxHistory>
            <!-- 所有日志文件总大小 -->
            <totalSizeCap>5GB</totalSizeCap>
        </rollingPolicy>

        <!-- 日志级别过滤器 -->
        <filter class="ch.qos.logback.classic.filter.LevelFilter">
            <level>DEBUG</level>
            <onMatch>ACCEPT</onMatch>
            <onMismatch>DENY</onMismatch>
        </filter>
    </appender>

    <!-- ==================== INFO 日志 ==================== -->
    <appender name="INFO_FILE" class="ch.qos.logback.core.rolling.RollingFileAppender">
        <file>${LOG_HOME}/info.log</file>

        <encoder>
            <pattern>${LOG_PATTERN}</pattern>
            <charset>UTF-8</charset>
        </encoder>

        <rollingPolicy class="ch.qos.logback.core.rolling.SizeAndTimeBasedRollingPolicy">
            <fileNamePattern>${LOG_HOME}/info/info.%d{yyyy-MM-dd}.%i.log</fileNamePattern>
            <maxFileSize>100MB</maxFileSize>
            <maxHistory>15</maxHistory>
            <totalSizeCap>5GB</totalSizeCap>
        </rollingPolicy>

        <filter class="ch.qos.logback.classic.filter.LevelFilter">
            <level>INFO</level>
            <onMatch>ACCEPT</onMatch>
            <onMismatch>DENY</onMismatch>
        </filter>
    </appender>

    <!-- ==================== WARN 日志 ==================== -->
    <appender name="WARN_FILE" class="ch.qos.logback.core.rolling.RollingFileAppender">
        <file>${LOG_HOME}/warn.log</file>

        <encoder>
            <pattern>${LOG_PATTERN}</pattern>
            <charset>UTF-8</charset>
        </encoder>

        <rollingPolicy class="ch.qos.logback.core.rolling.SizeAndTimeBasedRollingPolicy">
            <fileNamePattern>${LOG_HOME}/warn/warn.%d{yyyy-MM-dd}.%i.log</fileNamePattern>
            <maxFileSize>100MB</maxFileSize>
            <maxHistory>15</maxHistory>
            <totalSizeCap>5GB</totalSizeCap>
        </rollingPolicy>

        <filter class="ch.qos.logback.classic.filter.LevelFilter">
            <level>WARN</level>
            <onMatch>ACCEPT</onMatch>
            <onMismatch>DENY</onMismatch>
        </filter>
    </appender>

    <!-- ==================== ERROR 日志 ==================== -->
    <appender name="ERROR_FILE" class="ch.qos.logback.core.rolling.RollingFileAppender">
        <file>${LOG_HOME}/error.log</file>

        <encoder>
            <pattern>${LOG_PATTERN}</pattern>
            <charset>UTF-8</charset>
        </encoder>

        <rollingPolicy class="ch.qos.logback.core.rolling.SizeAndTimeBasedRollingPolicy">
            <fileNamePattern>${LOG_HOME}/error/error.%d{yyyy-MM-dd}.%i.log</fileNamePattern>
            <maxFileSize>100MB</maxFileSize>
            <maxHistory>15</maxHistory>
            <totalSizeCap>5GB</totalSizeCap>
        </rollingPolicy>

        <filter class="ch.qos.logback.classic.filter.LevelFilter">
            <level>ERROR</level>
            <onMatch>ACCEPT</onMatch>
            <onMismatch>DENY</onMismatch>
        </filter>
    </appender>

    <!-- ==================== 所有日志（归档） ==================== -->
    <appender name="ALL_FILE" class="ch.qos.logback.core.rolling.RollingFileAppender">
        <file>${LOG_HOME}/all.log</file>

        <encoder>
            <pattern>${LOG_PATTERN}</pattern>
            <charset>UTF-8</charset>
        </encoder>

        <rollingPolicy class="ch.qos.logback.core.rolling.SizeAndTimeBasedRollingPolicy">
            <fileNamePattern>${LOG_HOME}/all/all.%d{yyyy-MM-dd}.%i.log</fileNamePattern>
            <maxFileSize>100MB</maxFileSize>
            <maxHistory>15</maxHistory>
            <totalSizeCap>10GB</totalSizeCap>
        </rollingPolicy>
    </appender>

    <!-- ==================== 异步日志配置 ==================== -->
    <!-- 异步输出 DEBUG 日志 -->
    <appender name="ASYNC_DEBUG" class="ch.qos.logback.classic.AsyncAppender">
        <!-- 不丢失日志。默认如果队列的80%已满，则会丢弃TRACE、DEBUG、INFO级别的日志 -->
        <discardingThreshold>0</discardingThreshold>
        <!-- 更改默认的队列的深度，该值会影响性能。默认值为256 -->
        <queueSize>512</queueSize>
        <!-- 添加附加的appender，最多只能添加一个 -->
        <appender-ref ref="DEBUG_FILE"/>
    </appender>

    <!-- 异步输出 INFO 日志 -->
    <appender name="ASYNC_INFO" class="ch.qos.logback.classic.AsyncAppender">
        <discardingThreshold>0</discardingThreshold>
        <queueSize>512</queueSize>
        <appender-ref ref="INFO_FILE"/>
    </appender>

    <!-- 异步输出 WARN 日志 -->
    <appender name="ASYNC_WARN" class="ch.qos.logback.classic.AsyncAppender">
        <discardingThreshold>0</discardingThreshold>
        <queueSize>512</queueSize>
        <appender-ref ref="WARN_FILE"/>
    </appender>

    <!-- 异步输出 ERROR 日志 -->
    <appender name="ASYNC_ERROR" class="ch.qos.logback.classic.AsyncAppender">
        <discardingThreshold>0</discardingThreshold>
        <queueSize>512</queueSize>
        <appender-ref ref="ERROR_FILE"/>
    </appender>

    <!-- 异步输出 ALL 日志 -->
    <appender name="ASYNC_ALL" class="ch.qos.logback.classic.AsyncAppender">
        <discardingThreshold>0</discardingThreshold>
        <queueSize>1024</queueSize>
        <appender-ref ref="ALL_FILE"/>
    </appender>

    <!-- ==================== 特定包日志级别配置 ==================== -->
    <!-- Spring 框架日志 -->
    <logger name="org.springframework" level="INFO"/>

    <!-- MyBatis 日志 -->
    <logger name="com.baomidou.mybatisplus" level="INFO"/>
    <logger name="org.mybatis" level="INFO"/>

    <!-- SQL 日志（开发环境可以设置为 DEBUG） -->
    <logger name="com.yanwan.authcenter.mapper" level="DEBUG"/>

    <!-- Druid 数据源日志 -->
    <logger name="com.alibaba.druid" level="INFO"/>

    <!-- Redis 日志 -->
    <logger name="org.springframework.data.redis" level="INFO"/>
    <logger name="io.lettuce" level="INFO"/>

    <!-- Sa-Token 日志 -->
    <logger name="cn.dev33.satoken" level="INFO"/>

    <!-- Swagger/Knife4j 日志 -->
    <logger name="io.springfox" level="WARN"/>
    <logger name="com.github.xiaoymin" level="INFO"/>

    <!-- Netty 日志 -->
    <logger name="io.netty" level="WARN"/>

    <!-- 项目日志 -->
    <logger name="com.yanwan.authcenter" level="DEBUG" additivity="false">
        <appender-ref ref="CONSOLE"/>
        <appender-ref ref="ASYNC_DEBUG"/>
        <appender-ref ref="ASYNC_INFO"/>
        <appender-ref ref="ASYNC_WARN"/>
        <appender-ref ref="ASYNC_ERROR"/>
        <appender-ref ref="ASYNC_ALL"/>
    </logger>

    <!-- ==================== 环境配置 ==================== -->
    <!-- 开发环境 -->
    <springProfile name="dev">
        <root level="INFO">
            <appender-ref ref="CONSOLE"/>
            <appender-ref ref="ASYNC_DEBUG"/>
            <appender-ref ref="ASYNC_INFO"/>
            <appender-ref ref="ASYNC_WARN"/>
            <appender-ref ref="ASYNC_ERROR"/>
            <appender-ref ref="ASYNC_ALL"/>
        </root>
    </springProfile>

    <!-- 测试环境 -->
    <springProfile name="test">
        <root level="INFO">
            <appender-ref ref="CONSOLE"/>
            <appender-ref ref="ASYNC_INFO"/>
            <appender-ref ref="ASYNC_WARN"/>
            <appender-ref ref="ASYNC_ERROR"/>
            <appender-ref ref="ASYNC_ALL"/>
        </root>
    </springProfile>

    <!-- 生产环境 -->
    <springProfile name="prod">
        <root level="INFO">
            <appender-ref ref="ASYNC_INFO"/>
            <appender-ref ref="ASYNC_WARN"/>
            <appender-ref ref="ASYNC_ERROR"/>
            <appender-ref ref="ASYNC_ALL"/>
        </root>
    </springProfile>

    <!-- 默认配置（如果没有指定环境） -->
    <root level="INFO">
        <appender-ref ref="CONSOLE"/>
        <appender-ref ref="ASYNC_DEBUG"/>
        <appender-ref ref="ASYNC_INFO"/>
        <appender-ref ref="ASYNC_WARN"/>
        <appender-ref ref="ASYNC_ERROR"/>
        <appender-ref ref="ASYNC_ALL"/>
    </root>

</configuration>